LICENSE
glorious/__init__.py
glorious/devices.py
glorious/protocol.py
glorious-0.2.0.dist-info/LICENSE
glorious-0.2.0.dist-info/METADATA
glorious-0.2.0.dist-info/WHEEL
glorious-0.2.0.dist-info/RECORD
