Metadata-Version: 2.1
Name: glorious
Version: 0.2.0
Summary: Library to interface with Glorious devices
Home-page: https://github.com/kbidlack/glorious
License: MIT
Author: Kavi Bidlack
Author-email: ksbidlack@gmail.com
Requires-Python: >=3.11,<4.0
Classifier: License :: OSI Approved :: MIT License
Classifier: Programming Language :: Python :: 3
Classifier: Programming Language :: Python :: 3.11
Requires-Dist: hidapi (>=0.13.1,<0.14.0)
Project-URL: Repository, https://github.com/kbidlack/glorious
